nato_spell/__init__.py
nato_spell/sounds/0.wav
nato_spell/sounds/1.wav
nato_spell/sounds/2.wav
nato_spell/sounds/3.wav
nato_spell/sounds/4.wav
nato_spell/sounds/5.wav
nato_spell/sounds/6.wav
nato_spell/sounds/7.wav
nato_spell/sounds/8.wav
nato_spell/sounds/9.wav
nato_spell/sounds/CREDITS.md
nato_spell/sounds/a.wav
nato_spell/sounds/b.wav
nato_spell/sounds/c.wav
nato_spell/sounds/capital.wav
nato_spell/sounds/d.wav
nato_spell/sounds/e.wav
nato_spell/sounds/f.wav
nato_spell/sounds/g.wav
nato_spell/sounds/h.wav
nato_spell/sounds/i.wav
nato_spell/sounds/j.wav
nato_spell/sounds/k.wav
nato_spell/sounds/l.wav
nato_spell/sounds/m.wav
nato_spell/sounds/n.wav
nato_spell/sounds/o.wav
nato_spell/sounds/p.wav
nato_spell/sounds/q.wav
nato_spell/sounds/r.wav
nato_spell/sounds/s.wav
nato_spell/sounds/t.wav
nato_spell/sounds/u.wav
nato_spell/sounds/v.wav
nato_spell/sounds/w.wav
nato_spell/sounds/x.wav
nato_spell/sounds/y.wav
nato_spell/sounds/z.wav
nato_spell-0.3.1.dist-info/entry_points.txt
nato_spell-0.3.1.dist-info/WHEEL
nato_spell-0.3.1.dist-info/METADATA
nato_spell-0.3.1.dist-info/RECORD
