Metadata-Version: 2.1
Name: nato-spell
Version: 0.3.1
Summary: Spelling engine for the NATO phonetic alphabet
Home-page: https://github.com/Qu4tro/nato-spell/
License: MIT
Keywords: NATO,spelling,alphabet,phonetic
Author: Xavier Francisco
Author-email: xavier.n.francisco@gmail.com
Requires-Python: >=3.8,<4.0
Classifier: License :: OSI Approved :: MIT License
Classifier: Programming Language :: Python :: 3
Classifier: Programming Language :: Python :: 3.8
Project-URL: Repository, https://github.com/Qu4tro/nato-spell/
